sapiumai_common_tools/__init__.py
sapiumai_common_tools/config.py
sapiumai_common_tools/info.py
sapiumai_common_tools/logger.py
sapiumai_common_tools-0.1.1.dist-info/licenses/LICENSE
sapiumai_common_tools-0.1.1.dist-info/METADATA
sapiumai_common_tools-0.1.1.dist-info/WHEEL
sapiumai_common_tools-0.1.1.dist-info/top_level.txt
sapiumai_common_tools-0.1.1.dist-info/RECORD
