Metadata-Version: 2.4
Name: sapiumai_common_tools
Version: 0.1.1
Summary: Reusable utility functions
Author-email: Mauricio Falck <mfalck@sapium.ai>
License-Expression: MIT
License-File: LICENSE
Dynamic: license-file
